parasect/__init__.py
parasect/__main__.py
parasect/_helpers.py
parasect/build_lib.py
parasect/compare_lib.py
parasect/py.typed
parasect-1.2.0.dist-info/LICENSE.rst
parasect-1.2.0.dist-info/METADATA
parasect-1.2.0.dist-info/WHEEL
parasect-1.2.0.dist-info/entry_points.txt
parasect-1.2.0.dist-info/RECORD
