Metadata-Version: 2.1
Name: parasect
Version: 1.2.0
Summary: Utility for manipulating parameter sets for autopilots.
Home-page: https://github.com/AvyFly/parasect
License: MIT
Author: George Zogopoulos
Author-email: geo.zogop.papal@gmail.com
Requires-Python: >=3.8,<4.0
Classifier: Development Status :: 5 - Production/Stable
Classifier: License :: OSI Approved :: MIT License
Classifier: Programming Language :: Python :: 3
Classifier: Programming Language :: Python :: 3.8
Classifier: Programming Language :: Python :: 3.9
Classifier: Programming Language :: Python :: 3.10
Classifier: Programming Language :: Python :: 3.11
Requires-Dist: PyYAML (>=6.0,<7.0)
Requires-Dist: click (>=8.0.1,<9.0.0)
Requires-Dist: defusedxml (>=0.7.1,<0.8.0)
Requires-Dist: pydantic (>=1.9.1,<2.0.0)
Project-URL: Changelog, https://github.com/AvyFly/parasect/releases
Project-URL: Documentation, https://parasect.readthedocs.io
Project-URL: Repository, https://github.com/AvyFly/parasect
